shubham_test_library/__init__.py
shubham_test_library/core.py
shubham_test_library/utils.py
tests/__init__.py
tests/test_core.py
shubham_test_library-0.1.0.dist-info/LICENSE
shubham_test_library-0.1.0.dist-info/METADATA
shubham_test_library-0.1.0.dist-info/WHEEL
shubham_test_library-0.1.0.dist-info/top_level.txt
shubham_test_library-0.1.0.dist-info/RECORD
